{"updated":1783128485,"updated_str":"2026-07-04 01:28 UTC","health":{"ok":true,"open":166,"opened_30m":284,"closed_30m":171,"corrupt":0},"strategies":[{"name":"q_quicklock","closed":612,"mature":true,"win":58.7,"rug":21.9,"per_trade":0.533,"open":3,"open_value":144.6,"open_pnl_avg":33.0,"capital":426.28,"capital_pct":326.3},{"name":"q_scalp","closed":559,"mature":true,"win":58.3,"rug":19.9,"per_trade":0.472,"open":6,"open_value":3124.5,"open_pnl_avg":64.0,"capital":363.86,"capital_pct":263.9},{"name":"q_runner","closed":547,"mature":true,"win":59.0,"rug":21.2,"per_trade":0.468,"open":6,"open_value":269.9,"open_pnl_avg":64.0,"capital":356.12,"capital_pct":256.1},{"name":"q_patient","closed":540,"mature":true,"win":58.7,"rug":21.3,"per_trade":0.469,"open":6,"open_value":213.3,"open_pnl_avg":64.0,"capital":353.37,"capital_pct":253.4},{"name":"q_volconf","closed":515,"mature":true,"win":61.4,"rug":19.8,"per_trade":0.379,"open":4,"open_value":148.0,"open_pnl_avg":85.0,"capital":295.27,"capital_pct":195.3},{"name":"q_earlymom","closed":412,"mature":true,"win":58.3,"rug":20.6,"per_trade":0.418,"open":4,"open_value":213.6,"open_pnl_avg":85.0,"capital":272.02,"capital_pct":172.0},{"name":"q_core","closed":606,"mature":true,"win":53.5,"rug":24.9,"per_trade":0.261,"open":6,"open_value":307.2,"open_pnl_avg":64.0,"capital":258.29,"capital_pct":158.3},{"name":"q_synth","closed":152,"mature":true,"win":65.1,"rug":9.9,"per_trade":0.598,"open":2,"open_value":9734.0,"open_pnl_avg":39.0,"capital":190.91,"capital_pct":90.9},{"name":"q_peak","closed":250,"mature":true,"win":57.6,"rug":28.0,"per_trade":0.344,"open":3,"open_value":60500.7,"open_pnl_avg":117.0,"capital":186.08,"capital_pct":86.1},{"name":"q_trifecta","closed":105,"mature":true,"win":78.1,"rug":13.3,"per_trade":0.753,"open":3,"open_value":20050.6,"open_pnl_avg":106.0,"capital":179.06,"capital_pct":79.1},{"name":"q_apex_mom","closed":103,"mature":true,"win":68.0,"rug":19.4,"per_trade":0.737,"open":1,"open_value":7872.7,"open_pnl_avg":72.0,"capital":175.94,"capital_pct":75.9},{"name":"q_reality_20","closed":83,"mature":true,"win":73.5,"rug":14.5,"per_trade":0.889,"open":3,"open_value":738.5,"open_pnl_avg":106.0,"capital":173.8,"capital_pct":73.8},{"name":"q_reality_40","closed":82,"mature":true,"win":73.2,"rug":14.6,"per_trade":0.893,"open":3,"open_value":736.1,"open_pnl_avg":106.0,"capital":173.25,"capital_pct":73.2},{"name":"q_twoway","closed":379,"mature":true,"win":47.8,"rug":22.4,"per_trade":0.166,"open":3,"open_value":10352.7,"open_pnl_avg":106.0,"capital":162.74,"capital_pct":62.7},{"name":"q_fastlock","closed":180,"mature":true,"win":72.2,"rug":8.3,"per_trade":0.337,"open":1,"open_value":2101.2,"open_pnl_avg":6.0,"capital":160.72,"capital_pct":60.7},{"name":"q_strict","closed":146,"mature":true,"win":55.5,"rug":30.1,"per_trade":0.413,"open":2,"open_value":25478.0,"open_pnl_avg":156.0,"capital":160.24,"capital_pct":60.2},{"name":"q_midmom","closed":89,"mature":true,"win":68.5,"rug":19.1,"per_trade":0.631,"open":1,"open_value":10348.9,"open_pnl_avg":241.0,"capital":156.2,"capital_pct":56.2},{"name":"q_tight","closed":207,"mature":true,"win":52.7,"rug":29.0,"per_trade":0.245,"open":2,"open_value":20806.6,"open_pnl_avg":156.0,"capital":150.81,"capital_pct":50.8},{"name":"q_codex_alpha_20","closed":51,"mature":true,"win":78.4,"rug":11.8,"per_trade":0.942,"open":2,"open_value":275.8,"open_pnl_avg":156.0,"capital":148.03,"capital_pct":48.0},{"name":"q_codex_alpha_40","closed":51,"mature":true,"win":78.4,"rug":11.8,"per_trade":0.941,"open":2,"open_value":300.6,"open_pnl_avg":156.0,"capital":148.0,"capital_pct":48.0},{"name":"q_apex_mom_20","closed":25,"mature":true,"win":84.0,"rug":8.0,"per_trade":1.788,"open":1,"open_value":69.3,"open_pnl_avg":72.0,"capital":144.7,"capital_pct":44.7},{"name":"q_apex_mom_40","closed":25,"mature":true,"win":84.0,"rug":8.0,"per_trade":1.788,"open":1,"open_value":77.6,"open_pnl_avg":72.0,"capital":144.69,"capital_pct":44.7},{"name":"q_prime","closed":82,"mature":true,"win":63.4,"rug":26.8,"per_trade":0.542,"open":1,"open_value":7895.1,"open_pnl_avg":241.0,"capital":144.41,"capital_pct":44.4},{"name":"q_anchor_40","closed":31,"mature":true,"win":80.6,"rug":12.9,"per_trade":1.43,"open":1,"open_value":34.5,"open_pnl_avg":72.0,"capital":144.33,"capital_pct":44.3},{"name":"q_reality","closed":188,"mature":true,"win":66.0,"rug":20.2,"per_trade":0.234,"open":3,"open_value":35990.6,"open_pnl_avg":106.0,"capital":144.01,"capital_pct":44.0},{"name":"q_deepbook","closed":121,"mature":true,"win":53.7,"rug":36.4,"per_trade":0.356,"open":1,"open_value":3860.1,"open_pnl_avg":6.0,"capital":143.03,"capital_pct":43.0},{"name":"q_codex_alpha","closed":49,"mature":true,"win":77.6,"rug":14.3,"per_trade":0.876,"open":2,"open_value":583.5,"open_pnl_avg":156.0,"capital":142.94,"capital_pct":42.9},{"name":"q_deep","closed":235,"mature":true,"win":58.7,"rug":25.1,"per_trade":0.175,"open":2,"open_value":477.7,"open_pnl_avg":13.0,"capital":141.05,"capital_pct":41.1},{"name":"q_live","closed":61,"mature":true,"win":72.1,"rug":23.0,"per_trade":0.653,"open":3,"open_value":693.3,"open_pnl_avg":114.0,"capital":139.85,"capital_pct":39.9},{"name":"q_anchor","closed":128,"mature":true,"win":53.9,"rug":31.2,"per_trade":0.301,"open":1,"open_value":3616.6,"open_pnl_avg":72.0,"capital":138.47,"capital_pct":38.5},{"name":"q_anchor_20","closed":31,"mature":true,"win":77.4,"rug":16.1,"per_trade":1.201,"open":1,"open_value":34.5,"open_pnl_avg":72.0,"capital":137.22,"capital_pct":37.2},{"name":"q_trifecta_40","closed":38,"mature":true,"win":76.3,"rug":5.3,"per_trade":0.962,"open":2,"open_value":89.7,"open_pnl_avg":124.0,"capital":136.55,"capital_pct":36.5},{"name":"q_lockcore","closed":296,"mature":true,"win":42.2,"rug":27.0,"per_trade":0.121,"open":5,"open_value":3694.7,"open_pnl_avg":29.0,"capital":135.89,"capital_pct":35.9},{"name":"q_synth_40","closed":35,"mature":true,"win":68.6,"rug":5.7,"per_trade":0.991,"open":2,"open_value":78.1,"open_pnl_avg":39.0,"capital":134.68,"capital_pct":34.7},{"name":"q_apex_20","closed":27,"mature":true,"win":81.5,"rug":11.1,"per_trade":1.188,"open":2,"open_value":104.8,"open_pnl_avg":156.0,"capital":132.07,"capital_pct":32.1},{"name":"q_apex_40","closed":27,"mature":true,"win":81.5,"rug":11.1,"per_trade":1.188,"open":2,"open_value":115.2,"open_pnl_avg":156.0,"capital":132.07,"capital_pct":32.1},{"name":"q_nova","closed":27,"mature":true,"win":77.8,"rug":7.4,"per_trade":1.162,"open":1,"open_value":820.8,"open_pnl_avg":241.0,"capital":131.39,"capital_pct":31.4},{"name":"q_sweet","closed":68,"mature":true,"win":69.1,"rug":16.2,"per_trade":0.445,"open":1,"open_value":2593.3,"open_pnl_avg":241.0,"capital":130.26,"capital_pct":30.3},{"name":"q_apex","closed":91,"mature":true,"win":63.7,"rug":24.2,"per_trade":0.312,"open":2,"open_value":8591.1,"open_pnl_avg":156.0,"capital":128.41,"capital_pct":28.4},{"name":"q_codex_momentum_20","closed":19,"mature":false,"win":89.5,"rug":10.5,"per_trade":null,"open":2,"open_value":195.2,"open_pnl_avg":156.0,"capital":128.36,"capital_pct":28.4},{"name":"q_codex_momentum_40","closed":19,"mature":false,"win":89.5,"rug":10.5,"per_trade":null,"open":2,"open_value":218.7,"open_pnl_avg":156.0,"capital":128.36,"capital_pct":28.4},{"name":"q_midmom_20","closed":19,"mature":false,"win":89.5,"rug":10.5,"per_trade":null,"open":1,"open_value":133.2,"open_pnl_avg":241.0,"capital":128.36,"capital_pct":28.4},{"name":"q_midmom_40","closed":19,"mature":false,"win":89.5,"rug":10.5,"per_trade":null,"open":1,"open_value":149.3,"open_pnl_avg":241.0,"capital":128.36,"capital_pct":28.4},{"name":"q_codex_momentum","closed":19,"mature":false,"win":89.5,"rug":10.5,"per_trade":null,"open":2,"open_value":583.5,"open_pnl_avg":156.0,"capital":128.1,"capital_pct":28.1},{"name":"q_02","closed":36,"mature":true,"win":72.2,"rug":11.1,"per_trade":0.739,"open":2,"open_value":1662.6,"open_pnl_avg":156.0,"capital":126.61,"capital_pct":26.6},{"name":"q_prime_40","closed":30,"mature":true,"win":76.7,"rug":20.0,"per_trade":0.864,"open":1,"open_value":136.4,"open_pnl_avg":241.0,"capital":125.92,"capital_pct":25.9},{"name":"q_prime_20","closed":29,"mature":true,"win":75.9,"rug":20.7,"per_trade":0.833,"open":1,"open_value":111.2,"open_pnl_avg":241.0,"capital":124.16,"capital_pct":24.2},{"name":"q_live_40","closed":15,"mature":false,"win":86.7,"rug":6.7,"per_trade":null,"open":3,"open_value":128.4,"open_pnl_avg":114.0,"capital":121.87,"capital_pct":21.9},{"name":"q_trifecta_20","closed":20,"mature":true,"win":75.0,"rug":0.0,"per_trade":1.047,"open":2,"open_value":89.5,"open_pnl_avg":124.0,"capital":120.94,"capital_pct":20.9},{"name":"q_balanced","closed":108,"mature":true,"win":59.3,"rug":23.1,"per_trade":0.177,"open":1,"open_value":5691.3,"open_pnl_avg":241.0,"capital":119.13,"capital_pct":19.1},{"name":"q_live_20","closed":12,"mature":false,"win":83.3,"rug":8.3,"per_trade":null,"open":3,"open_value":128.4,"open_pnl_avg":114.0,"capital":116.86,"capital_pct":16.9},{"name":"q_shield","closed":12,"mature":false,"win":100.0,"rug":0.0,"per_trade":null,"open":0,"open_value":0,"open_pnl_avg":null,"capital":113.3,"capital_pct":13.3},{"name":"q_quicklock_40","closed":26,"mature":true,"win":46.2,"rug":3.8,"per_trade":0.344,"open":0,"open_value":0,"open_pnl_avg":null,"capital":108.95,"capital_pct":8.9},{"name":"q_fable5_deep100","closed":3,"mature":false,"win":100.0,"rug":0.0,"per_trade":null,"open":0,"open_value":0,"open_pnl_avg":null,"capital":108.24,"capital_pct":8.2},{"name":"q_01","closed":9,"mature":false,"win":77.8,"rug":0.0,"per_trade":null,"open":0,"open_value":0,"open_pnl_avg":null,"capital":107.49,"capital_pct":7.5},{"name":"q_lowrug","closed":39,"mature":true,"win":51.3,"rug":10.3,"per_trade":0.171,"open":0,"open_value":0,"open_pnl_avg":null,"capital":106.68,"capital_pct":6.7},{"name":"q_titan","closed":65,"mature":true,"win":58.5,"rug":27.7,"per_trade":0.097,"open":1,"open_value":1780.2,"open_pnl_avg":241.0,"capital":106.29,"capital_pct":6.3},{"name":"q_edge_tight","closed":3,"mature":false,"win":100.0,"rug":0.0,"per_trade":null,"open":0,"open_value":0,"open_pnl_avg":null,"capital":104.09,"capital_pct":4.1},{"name":"q_quicklock_20","closed":16,"mature":false,"win":43.8,"rug":6.2,"per_trade":null,"open":0,"open_value":0,"open_pnl_avg":null,"capital":103.83,"capital_pct":3.8},{"name":"q_fable5_velmicro_20","closed":5,"mature":false,"win":60.0,"rug":0.0,"per_trade":null,"open":0,"open_value":0,"open_pnl_avg":null,"capital":103.32,"capital_pct":3.3},{"name":"q_fable5_velmicro_40","closed":5,"mature":false,"win":60.0,"rug":0.0,"per_trade":null,"open":0,"open_value":0,"open_pnl_avg":null,"capital":103.32,"capital_pct":3.3},{"name":"q_fable5_velmicro","closed":5,"mature":false,"win":60.0,"rug":0.0,"per_trade":null,"open":0,"open_value":0,"open_pnl_avg":null,"capital":103.26,"capital_pct":3.3},{"name":"q_synth_20","closed":10,"mature":false,"win":50.0,"rug":10.0,"per_trade":null,"open":0,"open_value":0,"open_pnl_avg":null,"capital":102.53,"capital_pct":2.5},{"name":"q_edge_fast","closed":3,"mature":false,"win":100.0,"rug":0.0,"per_trade":null,"open":0,"open_value":0,"open_pnl_avg":null,"capital":102.49,"capital_pct":2.5},{"name":"q_fable5_veltight_20","closed":2,"mature":false,"win":100.0,"rug":0.0,"per_trade":null,"open":0,"open_value":0,"open_pnl_avg":null,"capital":100.72,"capital_pct":0.7},{"name":"q_fable5_veltight_40","closed":2,"mature":false,"win":100.0,"rug":0.0,"per_trade":null,"open":0,"open_value":0,"open_pnl_avg":null,"capital":100.72,"capital_pct":0.7},{"name":"q_fable5_veltight","closed":2,"mature":false,"win":100.0,"rug":0.0,"per_trade":null,"open":0,"open_value":0,"open_pnl_avg":null,"capital":100.7,"capital_pct":0.7},{"name":"q_edge_ride","closed":2,"mature":false,"win":100.0,"rug":0.0,"per_trade":null,"open":1,"open_value":85.3,"open_pnl_avg":241.0,"capital":100.52,"capital_pct":0.5},{"name":"q_edge_wide","closed":2,"mature":false,"win":100.0,"rug":0.0,"per_trade":null,"open":1,"open_value":85.3,"open_pnl_avg":241.0,"capital":100.52,"capital_pct":0.5},{"name":"q_fable5_v100","closed":1,"mature":false,"win":100.0,"rug":0.0,"per_trade":null,"open":0,"open_value":0,"open_pnl_avg":null,"capital":100.25,"capital_pct":0.2},{"name":"q_edge_deep","closed":0,"mature":false,"win":0,"rug":0,"per_trade":null,"open":1,"open_value":26.5,"open_pnl_avg":6.0,"capital":100.0,"capital_pct":0.0},{"name":"q_fable5_momo100","closed":0,"mature":false,"win":0,"rug":0,"per_trade":null,"open":0,"open_value":0,"open_pnl_avg":null,"capital":100.0,"capital_pct":0.0},{"name":"q_fable5_safe100","closed":0,"mature":false,"win":0,"rug":0,"per_trade":null,"open":0,"open_value":0,"open_pnl_avg":null,"capital":100.0,"capital_pct":0.0},{"name":"q_graddip100","closed":0,"mature":false,"win":0,"rug":0,"per_trade":null,"open":0,"open_value":0,"open_pnl_avg":null,"capital":100.0,"capital_pct":0.0},{"name":"q_fable5_velcore_40","closed":3,"mature":false,"win":66.7,"rug":0.0,"per_trade":null,"open":0,"open_value":0,"open_pnl_avg":null,"capital":99.75,"capital_pct":-0.2},{"name":"q_fable5_velcore","closed":3,"mature":false,"win":66.7,"rug":0.0,"per_trade":null,"open":0,"open_value":0,"open_pnl_avg":null,"capital":99.73,"capital_pct":-0.3},{"name":"q_fable5_velcore_20","closed":2,"mature":false,"win":50.0,"rug":0.0,"per_trade":null,"open":0,"open_value":0,"open_pnl_avg":null,"capital":99.5,"capital_pct":-0.5},{"name":"q_fastlock_20","closed":14,"mature":false,"win":57.1,"rug":14.3,"per_trade":null,"open":0,"open_value":0,"open_pnl_avg":null,"capital":99.37,"capital_pct":-0.6},{"name":"q_fable5_strict","closed":1,"mature":false,"win":0.0,"rug":0.0,"per_trade":null,"open":0,"open_value":0,"open_pnl_avg":null,"capital":99.03,"capital_pct":-1.0},{"name":"q_iron_exit100","closed":4,"mature":false,"win":75.0,"rug":25.0,"per_trade":null,"open":1,"open_value":68.3,"open_pnl_avg":241.0,"capital":98.58,"capital_pct":-1.4},{"name":"q_iron_ride100","closed":4,"mature":false,"win":75.0,"rug":25.0,"per_trade":null,"open":1,"open_value":68.3,"open_pnl_avg":241.0,"capital":98.58,"capital_pct":-1.4},{"name":"q_codex_40","closed":26,"mature":true,"win":53.8,"rug":15.4,"per_trade":-0.104,"open":0,"open_value":0,"open_pnl_avg":null,"capital":97.3,"capital_pct":-2.7},{"name":"q_iron_deep100","closed":1,"mature":false,"win":0.0,"rug":100.0,"per_trade":null,"open":1,"open_value":21.2,"open_pnl_avg":6.0,"capital":97.28,"capital_pct":-2.7},{"name":"q_fastlock_40","closed":15,"mature":false,"win":53.3,"rug":20.0,"per_trade":null,"open":0,"open_value":0,"open_pnl_avg":null,"capital":96.64,"capital_pct":-3.4},{"name":"q_fable5_wide100","closed":4,"mature":false,"win":25.0,"rug":25.0,"per_trade":null,"open":0,"open_value":0,"open_pnl_avg":null,"capital":95.35,"capital_pct":-4.7},{"name":"q_anchor_run","closed":117,"mature":true,"win":53.0,"rug":32.5,"per_trade":-0.145,"open":2,"open_value":10902.5,"open_pnl_avg":156.0,"capital":83.08,"capital_pct":-16.9},{"name":"q_elite","closed":59,"mature":true,"win":30.5,"rug":27.1,"per_trade":-0.788,"open":0,"open_value":0,"open_pnl_avg":null,"capital":53.53,"capital_pct":-46.5},{"name":"q_combo","closed":119,"mature":true,"win":39.5,"rug":27.7,"per_trade":-0.501,"open":1,"open_value":574.1,"open_pnl_avg":241.0,"capital":40.4,"capital_pct":-59.6},{"name":"q_momonly","closed":965,"mature":true,"win":38.0,"rug":19.0,"per_trade":-0.327,"open":5,"open_value":1797.0,"open_pnl_avg":70.0,"capital":-215.9,"capital_pct":-315.9},{"name":"q_score","closed":2299,"mature":true,"win":35.5,"rug":47.1,"per_trade":-0.809,"open":7,"open_value":8937.8,"open_pnl_avg":0.0,"capital":-1758.83,"capital_pct":-1858.8},{"name":"q_liqonly","closed":2918,"mature":true,"win":35.5,"rug":54.2,"per_trade":-0.922,"open":6,"open_value":157.6,"open_pnl_avg":27.0,"capital":-2591.06,"capital_pct":-2691.1}],"open_positions":{"q_lockcore":[{"sym":"Rpgbt","age_min":1.9,"size":581.0,"value":698.2,"pnl":20.0,"status":"win"},{"sym":"ALYCIA","age_min":5.0,"size":581.0,"value":617.1,"pnl":6.0,"status":"win"},{"sym":"bullsem","age_min":6.5,"size":581.0,"value":645.9,"pnl":11.0,"status":"win"},{"sym":"CapeVerde","age_min":11.7,"size":560.0,"value":768.3,"pnl":37.0,"status":"win"},{"sym":"FABLE","age_min":19.5,"size":560.0,"value":965.2,"pnl":72.0,"status":"win"}],"q_quicklock":[{"sym":"Rpgbt","age_min":1.9,"size":37.0,"value":44.4,"pnl":20.0,"status":"win"},{"sym":"ALYCIA","age_min":5.0,"size":37.0,"value":39.2,"pnl":6.0,"status":"win"},{"sym":"FABLE","age_min":19.5,"size":35.0,"value":61.0,"pnl":72.0,"status":"win"}],"q_deep":[{"sym":"Rpgbt","age_min":1.9,"size":211.0,"value":253.6,"pnl":20.0,"status":"win"},{"sym":"ALYCIA","age_min":5.0,"size":211.0,"value":224.1,"pnl":6.0,"status":"win"}],"q_earlymom":[{"sym":"Rpgbt","age_min":1.9,"size":30.0,"value":35.8,"pnl":20.0,"status":"win"},{"sym":"ALYCIA","age_min":5.0,"size":30.0,"value":31.7,"pnl":6.0,"status":"win"},{"sym":"Gamer","age_min":17.8,"size":28.0,"value":97.1,"pnl":241.0,"status":"win"},{"sym":"FABLE","age_min":19.5,"size":28.0,"value":49.0,"pnl":72.0,"status":"win"}],"q_runner":[{"sym":"Rpgbt","age_min":1.9,"size":28.0,"value":33.7,"pnl":20.0,"status":"win"},{"sym":"ALYCIA","age_min":5.0,"size":28.0,"value":29.8,"pnl":6.0,"status":"win"},{"sym":"bullsem","age_min":6.5,"size":28.0,"value":31.2,"pnl":11.0,"status":"win"},{"sym":"CapeVerde","age_min":11.7,"size":28.0,"value":38.5,"pnl":37.0,"status":"win"},{"sym":"Gamer","age_min":17.8,"size":27.0,"value":90.8,"pnl":241.0,"status":"win"},{"sym":"FABLE","age_min":19.5,"size":27.0,"value":45.9,"pnl":72.0,"status":"win"}],"q_volconf":[{"sym":"Rpgbt","age_min":1.9,"size":20.0,"value":24.0,"pnl":20.0,"status":"win"},{"sym":"ALYCIA","age_min":5.0,"size":20.0,"value":21.2,"pnl":6.0,"status":"win"},{"sym":"Gamer","age_min":17.8,"size":20.0,"value":68.3,"pnl":241.0,"status":"win"},{"sym":"FABLE","age_min":19.5,"size":20.0,"value":34.5,"pnl":72.0,"status":"win"}],"q_scalp":[{"sym":"Rpgbt","age_min":1.9,"size":327.0,"value":393.2,"pnl":20.0,"status":"win"},{"sym":"ALYCIA","age_min":5.0,"size":327.0,"value":347.5,"pnl":6.0,"status":"win"},{"sym":"bullsem","age_min":6.5,"size":327.0,"value":363.7,"pnl":11.0,"status":"win"},{"sym":"CapeVerde","age_min":11.7,"size":327.0,"value":449.3,"pnl":37.0,"status":"win"},{"sym":"Gamer","age_min":17.8,"size":306.0,"value":1043.5,"pnl":241.0,"status":"win"},{"sym":"FABLE","age_min":19.5,"size":306.0,"value":527.3,"pnl":72.0,"status":"win"}],"q_patient":[{"sym":"Rpgbt","age_min":1.9,"size":22.0,"value":26.5,"pnl":20.0,"status":"win"},{"sym":"ALYCIA","age_min":5.0,"size":22.0,"value":23.4,"pnl":6.0,"status":"win"},{"sym":"bullsem","age_min":6.5,"size":22.0,"value":24.5,"pnl":11.0,"status":"win"},{"sym":"CapeVerde","age_min":11.7,"size":22.0,"value":30.3,"pnl":37.0,"status":"win"},{"sym":"Gamer","age_min":17.8,"size":21.0,"value":72.1,"pnl":241.0,"status":"win"},{"sym":"FABLE","age_min":19.5,"size":21.0,"value":36.5,"pnl":72.0,"status":"win"}],"q_momonly":[{"sym":"Rpgbt","age_min":1.9,"size":218.0,"value":261.4,"pnl":20.0,"status":"win"},{"sym":"ALYCIA","age_min":5.0,"size":206.0,"value":218.6,"pnl":6.0,"status":"win"},{"sym":"bullsem","age_min":6.5,"size":206.0,"value":228.8,"pnl":11.0,"status":"win"},{"sym":"Gamer","age_min":17.8,"size":212.0,"value":722.9,"pnl":241.0,"status":"win"},{"sym":"FABLE","age_min":19.5,"size":212.0,"value":365.3,"pnl":72.0,"status":"win"}],"q_core":[{"sym":"Rpgbt","age_min":1.9,"size":32.0,"value":38.3,"pnl":20.0,"status":"win"},{"sym":"ALYCIA","age_min":5.0,"size":32.0,"value":33.8,"pnl":6.0,"status":"win"},{"sym":"bullsem","age_min":6.5,"size":32.0,"value":35.4,"pnl":11.0,"status":"win"},{"sym":"CapeVerde","age_min":11.7,"size":32.0,"value":43.7,"pnl":37.0,"status":"win"},{"sym":"Gamer","age_min":17.8,"size":30.0,"value":103.6,"pnl":241.0,"status":"win"},{"sym":"FABLE","age_min":19.5,"size":30.0,"value":52.4,"pnl":72.0,"status":"win"}],"widenet":[{"sym":"KEKIUS","age_min":2.8,"size":200.0,"value":182.0,"pnl":-9.0,"status":"loss"},{"sym":"USWR","age_min":6.5,"size":200.0,"value":251.3,"pnl":26.0,"status":"win"},{"sym":"USWR","age_min":6.5,"size":200.0,"value":261.1,"pnl":31.0,"status":"win"},{"sym":"BITCOIN","age_min":6.6,"size":200.0,"value":182.0,"pnl":-9.0,"status":"loss"},{"sym":"OPAL","age_min":7.6,"size":200.0,"value":182.0,"pnl":-9.0,"status":"loss"},{"sym":"EXTvbb","age_min":7.7,"size":200.0,"value":328.9,"pnl":64.0,"status":"win"},{"sym":"Calf","age_min":7.9,"size":200.0,"value":303.3,"pnl":52.0,"status":"win"},{"sym":"PLTEST","age_min":7.9,"size":200.0,"value":382.0,"pnl":91.0,"status":"win"},{"sym":"FIFA","age_min":7.9,"size":200.0,"value":250.1,"pnl":25.0,"status":"win"},{"sym":"PEIPEI","age_min":9.5,"size":200.0,"value":182.0,"pnl":-9.0,"status":"loss"},{"sym":"MKP","age_min":27.0,"size":200.0,"value":182.1,"pnl":-9.0,"status":"loss"},{"sym":"Mog","age_min":27.0,"size":200.0,"value":182.0,"pnl":-9.0,"status":"loss"},{"sym":"NTFS","age_min":27.1,"size":200.0,"value":0.0,"pnl":-100.0,"status":"loss"},{"sym":"VLCT","age_min":27.1,"size":200.0,"value":0.0,"pnl":-100.0,"status":"loss"},{"sym":"ALYCIA","age_min":27.1,"size":200.0,"value":716.3,"pnl":258.0,"status":"win"},{"sym":"Bullcoin","age_min":27.1,"size":200.0,"value":0.0,"pnl":-100.0,"status":"loss"},{"sym":"PEPEBULL","age_min":27.1,"size":200.0,"value":0.0,"pnl":-100.0,"status":"loss"},{"sym":"ASTEROID","age_min":27.7,"size":200.0,"value":182.0,"pnl":-9.0,"status":"loss"},{"sym":"CZ","age_min":30.9,"size":200.0,"value":316.9,"pnl":58.0,"status":"win"},{"sym":"C4","age_min":30.9,"size":200.0,"value":231.6,"pnl":16.0,"status":"win"}],"q_synth_40":[{"sym":"ALYCIA","age_min":5.0,"size":29.0,"value":30.9,"pnl":6.0,"status":"win"},{"sym":"FABLE","age_min":19.5,"size":27.0,"value":47.2,"pnl":72.0,"status":"win"}],"q_reality_40":[{"sym":"ALYCIA","age_min":5.0,"size":144.0,"value":152.6,"pnl":6.0,"status":"win"},{"sym":"Gamer","age_min":17.8,"size":110.0,"value":374.3,"pnl":241.0,"status":"win"},{"sym":"FABLE","age_min":19.5,"size":121.0,"value":209.2,"pnl":72.0,"status":"win"}],"q_reality_20":[{"sym":"ALYCIA","age_min":5.0,"size":146.0,"value":155.0,"pnl":6.0,"status":"win"},{"sym":"Gamer","age_min":17.8,"size":110.0,"value":374.3,"pnl":241.0,"status":"win"},{"sym":"FABLE","age_min":19.5,"size":121.0,"value":209.2,"pnl":72.0,"status":"win"}],"q_trifecta_40":[{"sym":"ALYCIA","age_min":5.0,"size":20.0,"value":21.4,"pnl":6.0,"status":"win"},{"sym":"Gamer","age_min":17.8,"size":20.0,"value":68.3,"pnl":241.0,"status":"win"}],"q_trifecta_20":[{"sym":"ALYCIA","age_min":5.0,"size":20.0,"value":21.2,"pnl":6.0,"status":"win"},{"sym":"Gamer","age_min":17.8,"size":20.0,"value":68.3,"pnl":241.0,"status":"win"}],"q_edge_deep":[{"sym":"ALYCIA","age_min":5.0,"size":25.0,"value":26.5,"pnl":6.0,"status":"win"}],"q_iron_deep100":[{"sym":"ALYCIA","age_min":5.0,"size":20.0,"value":21.2,"pnl":6.0,"status":"win"}],"q_trifecta":[{"sym":"ALYCIA","age_min":5.0,"size":3234.0,"value":3433.7,"pnl":6.0,"status":"win"},{"sym":"Gamer","age_min":17.8,"size":3234.0,"value":11039.1,"pnl":241.0,"status":"win"},{"sym":"FABLE","age_min":19.5,"size":3234.0,"value":5577.8,"pnl":72.0,"status":"win"}],"q_reality":[{"sym":"ALYCIA","age_min":5.0,"size":5663.0,"value":6011.8,"pnl":6.0,"status":"win"},{"sym":"Gamer","age_min":17.8,"size":5835.0,"value":19915.7,"pnl":241.0,"status":"win"},{"sym":"FABLE","age_min":19.5,"size":5835.0,"value":10063.1,"pnl":72.0,"status":"win"}],"q_deepbook":[{"sym":"ALYCIA","age_min":5.0,"size":3636.0,"value":3860.1,"pnl":6.0,"status":"win"}],"q_fastlock":[{"sym":"ALYCIA","age_min":5.0,"size":1979.0,"value":2101.2,"pnl":6.0,"status":"win"}],"q_synth":[{"sym":"ALYCIA","age_min":5.0,"size":3494.0,"value":3709.0,"pnl":6.0,"status":"win"},{"sym":"FABLE","age_min":19.5,"size":3494.0,"value":6025.0,"pnl":72.0,"status":"win"}],"q_twoway":[{"sym":"ALYCIA","age_min":5.0,"size":1601.0,"value":1699.1,"pnl":6.0,"status":"win"},{"sym":"Gamer","age_min":17.8,"size":1684.0,"value":5748.8,"pnl":241.0,"status":"win"},{"sym":"FABLE","age_min":19.5,"size":1684.0,"value":2904.8,"pnl":72.0,"status":"win"}],"q_live_40":[{"sym":"PEPE","age_min":5.7,"size":20.0,"value":25.6,"pnl":28.0,"status":"win"},{"sym":"Gamer","age_min":17.8,"size":20.0,"value":68.3,"pnl":241.0,"status":"win"},{"sym":"FABLE","age_min":19.5,"size":20.0,"value":34.5,"pnl":72.0,"status":"win"}],"q_live_20":[{"sym":"PEPE","age_min":5.7,"size":20.0,"value":25.6,"pnl":28.0,"status":"win"},{"sym":"Gamer","age_min":17.8,"size":20.0,"value":68.3,"pnl":241.0,"status":"win"},{"sym":"FABLE","age_min":19.5,"size":20.0,"value":34.5,"pnl":72.0,"status":"win"}],"q_live":[{"sym":"PEPE","age_min":5.7,"size":86.0,"value":109.8,"pnl":28.0,"status":"win"},{"sym":"Gamer","age_min":17.8,"size":110.0,"value":374.3,"pnl":241.0,"status":"win"},{"sym":"FABLE","age_min":19.5,"size":121.0,"value":209.2,"pnl":72.0,"status":"win"}],"q_liqonly":[{"sym":"bullsem","age_min":6.5,"size":24.0,"value":26.4,"pnl":11.0,"status":"win"},{"sym":"Calf","age_min":7.9,"size":21.0,"value":31.8,"pnl":52.0,"status":"win"},{"sym":"Ogre","age_min":11.7,"size":20.0,"value":22.0,"pnl":10.0,"status":"win"},{"sym":"ALYCIA","age_min":12.3,"size":20.0,"value":23.9,"pnl":20.0,"status":"win"},{"sym":"SKEIN","age_min":17.8,"size":20.0,"value":24.5,"pnl":23.0,"status":"win"},{"sym":"manlet","age_min":26.1,"size":20.0,"value":29.0,"pnl":45.0,"status":"win"}],"q_peak":[{"sym":"CapeVerde","age_min":11.7,"size":9293.0,"value":12756.5,"pnl":37.0,"status":"win"},{"sym":"Gamer","age_min":17.8,"size":9293.0,"value":31717.8,"pnl":241.0,"status":"win"},{"sym":"FABLE","age_min":19.5,"size":9293.0,"value":16026.4,"pnl":72.0,"status":"win"}],"q_apex_40":[{"sym":"Gamer","age_min":17.8,"size":22.0,"value":76.5,"pnl":241.0,"status":"win"},{"sym":"FABLE","age_min":19.5,"size":22.0,"value":38.7,"pnl":72.0,"status":"win"}],"q_apex_20":[{"sym":"Gamer","age_min":17.8,"size":20.0,"value":69.6,"pnl":241.0,"status":"win"},{"sym":"FABLE","age_min":19.5,"size":20.0,"value":35.2,"pnl":72.0,"status":"win"}],"q_prime_40":[{"sym":"Gamer","age_min":17.8,"size":40.0,"value":136.4,"pnl":241.0,"status":"win"}],"q_prime_20":[{"sym":"Gamer","age_min":17.8,"size":33.0,"value":111.2,"pnl":241.0,"status":"win"}],"q_midmom_40":[{"sym":"Gamer","age_min":17.8,"size":44.0,"value":149.3,"pnl":241.0,"status":"win"}],"q_midmom_20":[{"sym":"Gamer","age_min":17.8,"size":39.0,"value":133.2,"pnl":241.0,"status":"win"}],"q_codex_momentum_40":[{"sym":"Gamer","age_min":17.8,"size":43.0,"value":145.3,"pnl":241.0,"status":"win"},{"sym":"FABLE","age_min":19.5,"size":43.0,"value":73.4,"pnl":72.0,"status":"win"}],"q_codex_momentum_20":[{"sym":"Gamer","age_min":17.8,"size":38.0,"value":129.7,"pnl":241.0,"status":"win"},{"sym":"FABLE","age_min":19.5,"size":38.0,"value":65.5,"pnl":72.0,"status":"win"}],"q_codex_alpha_40":[{"sym":"Gamer","age_min":17.8,"size":58.0,"value":199.7,"pnl":241.0,"status":"win"},{"sym":"FABLE","age_min":19.5,"size":58.0,"value":100.9,"pnl":72.0,"status":"win"}],"q_codex_alpha_20":[{"sym":"Gamer","age_min":17.8,"size":54.0,"value":183.2,"pnl":241.0,"status":"win"},{"sym":"FABLE","age_min":19.5,"size":54.0,"value":92.6,"pnl":72.0,"status":"win"}],"q_codex_momentum":[{"sym":"Gamer","age_min":17.8,"size":110.0,"value":374.3,"pnl":241.0,"status":"win"},{"sym":"FABLE","age_min":19.5,"size":121.0,"value":209.2,"pnl":72.0,"status":"win"}],"q_codex_alpha":[{"sym":"Gamer","age_min":17.8,"size":110.0,"value":374.3,"pnl":241.0,"status":"win"},{"sym":"FABLE","age_min":19.5,"size":121.0,"value":209.2,"pnl":72.0,"status":"win"}],"q_edge_wide":[{"sym":"Gamer","age_min":17.8,"size":25.0,"value":85.3,"pnl":241.0,"status":"win"}],"q_edge_ride":[{"sym":"Gamer","age_min":17.8,"size":25.0,"value":85.3,"pnl":241.0,"status":"win"}],"q_iron_ride100":[{"sym":"Gamer","age_min":17.8,"size":20.0,"value":68.3,"pnl":241.0,"status":"win"}],"q_iron_exit100":[{"sym":"Gamer","age_min":17.8,"size":20.0,"value":68.3,"pnl":241.0,"status":"win"}],"q_nova":[{"sym":"Gamer","age_min":17.8,"size":241.0,"value":820.8,"pnl":241.0,"status":"win"}],"q_02":[{"sym":"Gamer","age_min":17.8,"size":324.0,"value":1104.5,"pnl":241.0,"status":"win"},{"sym":"FABLE","age_min":19.5,"size":324.0,"value":558.1,"pnl":72.0,"status":"win"}],"q_apex":[{"sym":"Gamer","age_min":17.8,"size":1672.0,"value":5707.3,"pnl":241.0,"status":"win"},{"sym":"FABLE","age_min":19.5,"size":1672.0,"value":2883.8,"pnl":72.0,"status":"win"}],"q_anchor_run":[{"sym":"Gamer","age_min":17.8,"size":2122.0,"value":7242.8,"pnl":241.0,"status":"win"},{"sym":"FABLE","age_min":19.5,"size":2122.0,"value":3659.7,"pnl":72.0,"status":"win"}],"q_titan":[{"sym":"Gamer","age_min":17.8,"size":522.0,"value":1780.2,"pnl":241.0,"status":"win"}],"q_balanced":[{"sym":"Gamer","age_min":17.8,"size":1668.0,"value":5691.3,"pnl":241.0,"status":"win"}],"q_sweet":[{"sym":"Gamer","age_min":17.8,"size":760.0,"value":2593.3,"pnl":241.0,"status":"win"}],"q_midmom":[{"sym":"Gamer","age_min":17.8,"size":3032.0,"value":10348.9,"pnl":241.0,"status":"win"}],"q_prime":[{"sym":"Gamer","age_min":17.8,"size":2313.0,"value":7895.1,"pnl":241.0,"status":"win"}],"q_combo":[{"sym":"Gamer","age_min":17.8,"size":168.0,"value":574.1,"pnl":241.0,"status":"win"}],"q_strict":[{"sym":"Gamer","age_min":17.8,"size":4959.0,"value":16925.7,"pnl":241.0,"status":"win"},{"sym":"FABLE","age_min":19.5,"size":4959.0,"value":8552.3,"pnl":72.0,"status":"win"}],"q_tight":[{"sym":"Gamer","age_min":17.8,"size":4050.0,"value":13822.4,"pnl":241.0,"status":"win"},{"sym":"FABLE","age_min":19.5,"size":4050.0,"value":6984.2,"pnl":72.0,"status":"win"}],"q_anchor_40":[{"sym":"FABLE","age_min":19.5,"size":20.0,"value":34.5,"pnl":72.0,"status":"win"}],"q_anchor_20":[{"sym":"FABLE","age_min":19.5,"size":20.0,"value":34.5,"pnl":72.0,"status":"win"}],"q_apex_mom_40":[{"sym":"FABLE","age_min":19.5,"size":45.0,"value":77.6,"pnl":72.0,"status":"win"}],"q_apex_mom_20":[{"sym":"FABLE","age_min":19.5,"size":40.0,"value":69.3,"pnl":72.0,"status":"win"}],"q_apex_mom":[{"sym":"FABLE","age_min":19.5,"size":4565.0,"value":7872.7,"pnl":72.0,"status":"win"}],"q_anchor":[{"sym":"FABLE","age_min":19.5,"size":2097.0,"value":3616.6,"pnl":72.0,"status":"win"}],"q_score":[{"sym":"SEMAN","age_min":25.0,"size":1277.0,"value":1336.9,"pnl":5.0,"status":"win"},{"sym":"BULLANA","age_min":25.0,"size":1277.0,"value":1071.2,"pnl":-16.0,"status":"loss"},{"sym":"Bullcoin","age_min":25.1,"size":1277.0,"value":1002.3,"pnl":-21.0,"status":"loss"},{"sym":"FABLE","age_min":25.1,"size":1277.0,"value":1051.1,"pnl":-18.0,"status":"loss"},{"sym":"BABYANSEM","age_min":25.1,"size":1277.0,"value":1635.7,"pnl":28.0,"status":"win"},{"sym":"ELON","age_min":25.1,"size":1277.0,"value":988.3,"pnl":-23.0,"status":"loss"},{"sym":"manlet","age_min":26.1,"size":1277.0,"value":1852.3,"pnl":45.0,"status":"win"}]},"feed":[{"strat":"q_liqonly","sym":"PEPE","ago_min":0.8,"reason":"reality_lock_trail","pnl":13.0},{"strat":"q_liqonly","sym":"CZ","ago_min":0.8,"reason":"recycle_dead","pnl":45.0},{"strat":"q_quicklock","sym":"Gamer","ago_min":1.5,"reason":"take_profit_full","pnl":152.0},{"strat":"q_synth","sym":"Gamer","ago_min":1.5,"reason":"take_profit_full","pnl":120.0},{"strat":"q_lockcore","sym":"Gamer","ago_min":1.5,"reason":"take_profit_full","pnl":147.0},{"strat":"q_anchor","sym":"Gamer","ago_min":1.5,"reason":"take_profit_full","pnl":133.0},{"strat":"q_apex_mom","sym":"Gamer","ago_min":1.5,"reason":"take_profit_full","pnl":111.0},{"strat":"q_edge_tight","sym":"Gamer","ago_min":1.5,"reason":"take_profit_full","pnl":152.0},{"strat":"q_apex_mom_20","sym":"Gamer","ago_min":1.5,"reason":"take_profit_full","pnl":152.0},{"strat":"q_apex_mom_40","sym":"Gamer","ago_min":1.5,"reason":"take_profit_full","pnl":152.0},{"strat":"q_anchor_20","sym":"Gamer","ago_min":1.5,"reason":"take_profit_full","pnl":152.0},{"strat":"q_anchor_40","sym":"Gamer","ago_min":1.5,"reason":"take_profit_full","pnl":152.0},{"strat":"q_synth_40","sym":"Gamer","ago_min":1.5,"reason":"take_profit_full","pnl":152.0},{"strat":"q_momonly","sym":"CapeVerde","ago_min":2.3,"reason":"reality_lock_trail","pnl":43.0},{"strat":"widenet","sym":"FUKC","ago_min":3.9,"reason":"stop_loss","pnl":-42.0},{"strat":"q_nova","sym":"FABLE","ago_min":5.4,"reason":"reality_lock_trail","pnl":33.0},{"strat":"q_liqonly","sym":"ALYCIA","ago_min":5.7,"reason":"reality_rotate_lock","pnl":117.0},{"strat":"q_liqonly","sym":"CapeVerde","ago_min":7.0,"reason":"reality_lock_trail","pnl":26.0},{"strat":"q_fastlock","sym":"FABLE","ago_min":7.8,"reason":"take_profit_full","pnl":29.0},{"strat":"q_momonly","sym":"ALYCIA","ago_min":9.3,"reason":"paper_rug","pnl":-100.0},{"strat":"q_tight","sym":"MESSI","ago_min":10.8,"reason":"paper_rug","pnl":-100.0},{"strat":"q_twoway","sym":"MESSI","ago_min":10.8,"reason":"paper_rug","pnl":-100.0},{"strat":"q_quicklock","sym":"MESSI","ago_min":10.8,"reason":"paper_rug","pnl":-100.0},{"strat":"q_lockcore","sym":"MESSI","ago_min":10.8,"reason":"paper_rug","pnl":-100.0},{"strat":"q_prime","sym":"MESSI","ago_min":10.8,"reason":"paper_rug","pnl":-100.0},{"strat":"q_midmom","sym":"MESSI","ago_min":10.8,"reason":"paper_rug","pnl":-100.0},{"strat":"q_anchor","sym":"MESSI","ago_min":10.8,"reason":"paper_rug","pnl":-100.0},{"strat":"q_anchor_run","sym":"MESSI","ago_min":10.8,"reason":"paper_rug","pnl":-100.0},{"strat":"q_apex_mom","sym":"MESSI","ago_min":10.8,"reason":"paper_rug","pnl":-100.0},{"strat":"q_reality","sym":"MESSI","ago_min":10.8,"reason":"paper_rug","pnl":-100.0},{"strat":"q_prime_20","sym":"MESSI","ago_min":10.8,"reason":"paper_rug","pnl":-100.0},{"strat":"q_prime_40","sym":"MESSI","ago_min":10.8,"reason":"paper_rug","pnl":-100.0},{"strat":"widenet","sym":"ASTEROID","ago_min":11.5,"reason":"max_age_widenet","pnl":-2.0},{"strat":"widenet","sym":"NEX","ago_min":11.5,"reason":"max_age_widenet","pnl":-4.0},{"strat":"widenet","sym":"IN","ago_min":11.5,"reason":"max_age_widenet","pnl":-1.0},{"strat":"widenet","sym":"NES","ago_min":11.5,"reason":"max_age_widenet","pnl":-2.0},{"strat":"widenet","sym":"RDNT","ago_min":11.5,"reason":"max_age_widenet","pnl":-2.0},{"strat":"widenet","sym":"ARX","ago_min":11.5,"reason":"max_age_widenet","pnl":-2.0},{"strat":"widenet","sym":"ARK","ago_min":11.5,"reason":"max_age_widenet","pnl":-1.0},{"strat":"widenet","sym":"SIREN","ago_min":11.5,"reason":"max_age_widenet","pnl":-1.0},{"strat":"widenet","sym":"FLORK","ago_min":11.5,"reason":"max_age_widenet","pnl":-1.0},{"strat":"widenet","sym":"LAB","ago_min":11.5,"reason":"max_age_widenet","pnl":-1.0},{"strat":"q_liqonly","sym":"Gamer","ago_min":11.7,"reason":"reality_rotate_lock","pnl":37.0},{"strat":"q_liqonly","sym":"AMERICA250","ago_min":11.7,"reason":"reality_rotate_lock","pnl":62.0},{"strat":"q_core","sym":"MESSI","ago_min":13.0,"reason":"reality_lock_trail","pnl":19.0},{"strat":"q_liqonly","sym":"MESSI","ago_min":13.0,"reason":"reality_lock_trail","pnl":19.0},{"strat":"q_momonly","sym":"MESSI","ago_min":13.0,"reason":"reality_lock_trail","pnl":17.0},{"strat":"q_patient","sym":"MESSI","ago_min":13.0,"reason":"reality_lock_trail","pnl":19.0},{"strat":"q_scalp","sym":"MESSI","ago_min":13.0,"reason":"reality_lock_trail","pnl":16.0},{"strat":"q_volconf","sym":"MESSI","ago_min":13.0,"reason":"reality_lock_trail","pnl":19.0}],"note":"REALITY MODE: numbers = what $2.5/trade LIVE would yield. Rug/honeypot/noprice=-100%, moon capped +200%, real fees+slippage+$0.12 fixed gas. $100 bankroll."}