{"updated":1783672330,"updated_str":"2026-07-10 08:32 UTC","reset_epoch":1783128544,"bankroll":60.0,"unit_usd":2.5,"health":{"ok":true,"open":124,"opened_30m":200,"closed_30m":176,"corrupt":0},"strategies":[{"name":"q_apex_mom_20","closed":192,"mature":true,"win":66.1,"rug":30.7,"per_trade":0.437,"open":0,"open_value":0,"open_pnl_avg":null,"capital":143.89,"capital_pct":139.8},{"name":"q_apex_mom_40","closed":192,"mature":true,"win":66.1,"rug":30.7,"per_trade":0.437,"open":0,"open_value":0,"open_pnl_avg":null,"capital":143.83,"capital_pct":139.7},{"name":"q_edge_fast","closed":191,"mature":true,"win":74.3,"rug":22.0,"per_trade":0.231,"open":0,"open_value":0,"open_pnl_avg":null,"capital":104.1,"capital_pct":73.5},{"name":"q_edge_tight","closed":94,"mature":true,"win":71.3,"rug":24.5,"per_trade":0.432,"open":0,"open_value":0,"open_pnl_avg":null,"capital":100.65,"capital_pct":67.8},{"name":"q_codex_momentum_20","closed":193,"mature":true,"win":59.6,"rug":37.3,"per_trade":0.143,"open":0,"open_value":0,"open_pnl_avg":null,"capital":87.5,"capital_pct":45.8},{"name":"q_codex_momentum_40","closed":193,"mature":true,"win":59.6,"rug":37.3,"per_trade":0.142,"open":0,"open_value":0,"open_pnl_avg":null,"capital":87.46,"capital_pct":45.8},{"name":"q_codex_momentum","closed":193,"mature":true,"win":59.6,"rug":37.3,"per_trade":0.14,"open":0,"open_value":0,"open_pnl_avg":null,"capital":87.1,"capital_pct":45.2},{"name":"q_midmom_20","closed":164,"mature":true,"win":60.4,"rug":37.2,"per_trade":0.161,"open":0,"open_value":0,"open_pnl_avg":null,"capital":86.45,"capital_pct":44.1},{"name":"q_midmom_40","closed":164,"mature":true,"win":60.4,"rug":37.2,"per_trade":0.161,"open":0,"open_value":0,"open_pnl_avg":null,"capital":86.41,"capital_pct":44.0},{"name":"q_fable5_velmicro_20","closed":81,"mature":true,"win":59.3,"rug":30.9,"per_trade":0.284,"open":0,"open_value":0,"open_pnl_avg":null,"capital":83.01,"capital_pct":38.4},{"name":"q_fable5_velmicro_40","closed":81,"mature":true,"win":59.3,"rug":30.9,"per_trade":0.284,"open":0,"open_value":0,"open_pnl_avg":null,"capital":82.97,"capital_pct":38.3},{"name":"q_fable5_velmicro","closed":81,"mature":true,"win":59.3,"rug":30.9,"per_trade":0.275,"open":0,"open_value":0,"open_pnl_avg":null,"capital":82.31,"capital_pct":37.2},{"name":"q_fable5_velcore","closed":66,"mature":true,"win":60.6,"rug":33.3,"per_trade":0.253,"open":0,"open_value":0,"open_pnl_avg":null,"capital":76.7,"capital_pct":27.8},{"name":"q_shield","closed":117,"mature":true,"win":72.6,"rug":23.9,"per_trade":0.124,"open":0,"open_value":0,"open_pnl_avg":null,"capital":74.56,"capital_pct":24.3},{"name":"q_fable5_strict","closed":48,"mature":true,"win":60.4,"rug":33.3,"per_trade":0.26,"open":0,"open_value":0,"open_pnl_avg":null,"capital":72.5,"capital_pct":20.8},{"name":"q_fable5_v100","closed":59,"mature":true,"win":57.6,"rug":35.6,"per_trade":0.174,"open":0,"open_value":0,"open_pnl_avg":null,"capital":70.28,"capital_pct":17.1},{"name":"q_apex_ride","closed":9,"mature":false,"win":77.8,"rug":11.1,"per_trade":null,"open":0,"open_value":0,"open_pnl_avg":null,"capital":68.9,"capital_pct":14.8},{"name":"q_fable5_safe100","closed":13,"mature":false,"win":76.9,"rug":7.7,"per_trade":null,"open":0,"open_value":0,"open_pnl_avg":null,"capital":68.2,"capital_pct":13.7},{"name":"q_iron_ride100","closed":188,"mature":true,"win":59.6,"rug":35.6,"per_trade":0.035,"open":0,"open_value":0,"open_pnl_avg":null,"capital":66.58,"capital_pct":11.0},{"name":"q_edge_ride","closed":188,"mature":true,"win":59.6,"rug":35.6,"per_trade":0.034,"open":0,"open_value":0,"open_pnl_avg":null,"capital":66.43,"capital_pct":10.7},{"name":"q_elite","closed":40,"mature":true,"win":52.5,"rug":37.5,"per_trade":0.103,"open":0,"open_value":0,"open_pnl_avg":null,"capital":64.13,"capital_pct":6.9},{"name":"q_01","closed":66,"mature":true,"win":56.1,"rug":37.9,"per_trade":0.036,"open":0,"open_value":0,"open_pnl_avg":null,"capital":62.39,"capital_pct":4.0},{"name":"q_iron_exit100","closed":191,"mature":true,"win":58.6,"rug":36.1,"per_trade":0.004,"open":0,"open_value":0,"open_pnl_avg":null,"capital":60.84,"capital_pct":1.4},{"name":"q_fable5_momo100","closed":50,"mature":true,"win":56.0,"rug":44.0,"per_trade":0.012,"open":0,"open_value":0,"open_pnl_avg":null,"capital":60.58,"capital_pct":1.0},{"name":"q_codex_40","closed":0,"mature":false,"win":0,"rug":0,"per_trade":null,"open":0,"open_value":0,"open_pnl_avg":null,"capital":60.0,"capital_pct":0.0},{"name":"q_fable5_velcore_20","closed":0,"mature":false,"win":0,"rug":0,"per_trade":null,"open":0,"open_value":0,"open_pnl_avg":null,"capital":60.0,"capital_pct":0.0},{"name":"q_fastlock_20","closed":0,"mature":false,"win":0,"rug":0,"per_trade":null,"open":0,"open_value":0,"open_pnl_avg":null,"capital":60.0,"capital_pct":0.0},{"name":"q_fastlock_40","closed":0,"mature":false,"win":0,"rug":0,"per_trade":null,"open":0,"open_value":0,"open_pnl_avg":null,"capital":60.0,"capital_pct":0.0},{"name":"q_graddip100","closed":0,"mature":false,"win":0,"rug":0,"per_trade":null,"open":0,"open_value":0,"open_pnl_avg":null,"capital":60.0,"capital_pct":0.0},{"name":"q_quicklock_20","closed":0,"mature":false,"win":0,"rug":0,"per_trade":null,"open":0,"open_value":0,"open_pnl_avg":null,"capital":60.0,"capital_pct":0.0},{"name":"q_quicklock_40","closed":0,"mature":false,"win":0,"rug":0,"per_trade":null,"open":0,"open_value":0,"open_pnl_avg":null,"capital":60.0,"capital_pct":0.0},{"name":"q_rebound","closed":0,"mature":false,"win":0,"rug":0,"per_trade":null,"open":0,"open_value":0,"open_pnl_avg":null,"capital":60.0,"capital_pct":0.0},{"name":"q_synth_20","closed":0,"mature":false,"win":0,"rug":0,"per_trade":null,"open":0,"open_value":0,"open_pnl_avg":null,"capital":60.0,"capital_pct":0.0},{"name":"q_quiet_ride","closed":17,"mature":false,"win":52.9,"rug":29.4,"per_trade":null,"open":0,"open_value":0,"open_pnl_avg":null,"capital":58.59,"capital_pct":-2.4},{"name":"q_fable5_veltight","closed":43,"mature":true,"win":53.5,"rug":39.5,"per_trade":-0.05,"open":0,"open_value":0,"open_pnl_avg":null,"capital":57.86,"capital_pct":-3.6},{"name":"q_fable5_veltight_20","closed":1,"mature":false,"win":0.0,"rug":100.0,"per_trade":null,"open":0,"open_value":0,"open_pnl_avg":null,"capital":57.27,"capital_pct":-4.5},{"name":"q_sweet_ride","closed":1,"mature":false,"win":0.0,"rug":100.0,"per_trade":null,"open":0,"open_value":0,"open_pnl_avg":null,"capital":57.27,"capital_pct":-4.5},{"name":"q_codex_ride","closed":1,"mature":false,"win":0.0,"rug":100.0,"per_trade":null,"open":0,"open_value":0,"open_pnl_avg":null,"capital":57.27,"capital_pct":-4.5},{"name":"q_balanced_ride","closed":14,"mature":false,"win":50.0,"rug":42.9,"per_trade":null,"open":0,"open_value":0,"open_pnl_avg":null,"capital":55.29,"capital_pct":-7.9},{"name":"q_fable5_wide100","closed":2,"mature":false,"win":0.0,"rug":100.0,"per_trade":null,"open":0,"open_value":0,"open_pnl_avg":null,"capital":54.55,"capital_pct":-9.1},{"name":"q_fable5_veltight_40","closed":6,"mature":false,"win":33.3,"rug":33.3,"per_trade":null,"open":0,"open_value":0,"open_pnl_avg":null,"capital":52.85,"capital_pct":-11.9},{"name":"q_regime50","closed":9,"mature":false,"win":33.3,"rug":33.3,"per_trade":null,"open":0,"open_value":0,"open_pnl_avg":null,"capital":52.36,"capital_pct":-12.7},{"name":"q_apex_mom","closed":192,"mature":true,"win":58.9,"rug":38.0,"per_trade":-0.042,"open":0,"open_value":0,"open_pnl_avg":null,"capital":51.85,"capital_pct":-13.6},{"name":"q_fable5_velcore_40","closed":8,"mature":false,"win":37.5,"rug":37.5,"per_trade":null,"open":0,"open_value":0,"open_pnl_avg":null,"capital":51.22,"capital_pct":-14.6},{"name":"q_calm","closed":30,"mature":true,"win":50.0,"rug":33.3,"per_trade":-0.37,"open":0,"open_value":0,"open_pnl_avg":null,"capital":48.91,"capital_pct":-18.5},{"name":"q_live","closed":160,"mature":true,"win":55.6,"rug":41.2,"per_trade":-0.072,"open":0,"open_value":0,"open_pnl_avg":null,"capital":48.42,"capital_pct":-19.3},{"name":"q_live_20","closed":160,"mature":true,"win":55.6,"rug":41.2,"per_trade":-0.076,"open":0,"open_value":0,"open_pnl_avg":null,"capital":47.84,"capital_pct":-20.3},{"name":"q_live_40","closed":160,"mature":true,"win":55.6,"rug":41.2,"per_trade":-0.076,"open":0,"open_value":0,"open_pnl_avg":null,"capital":47.81,"capital_pct":-20.3},{"name":"q_codex_alpha_20","closed":410,"mature":true,"win":53.7,"rug":40.2,"per_trade":-0.034,"open":0,"open_value":0,"open_pnl_avg":null,"capital":46.16,"capital_pct":-23.1},{"name":"q_codex_alpha_40","closed":410,"mature":true,"win":53.7,"rug":40.2,"per_trade":-0.034,"open":0,"open_value":0,"open_pnl_avg":null,"capital":46.08,"capital_pct":-23.2},{"name":"q_edge_wide","closed":359,"mature":true,"win":56.3,"rug":37.3,"per_trade":-0.04,"open":0,"open_value":0,"open_pnl_avg":null,"capital":45.8,"capital_pct":-23.7},{"name":"q_codex_alpha","closed":410,"mature":true,"win":53.7,"rug":40.2,"per_trade":-0.035,"open":0,"open_value":0,"open_pnl_avg":null,"capital":45.53,"capital_pct":-24.1},{"name":"q_iron_deep100","closed":8,"mature":false,"win":25.0,"rug":75.0,"per_trade":null,"open":0,"open_value":0,"open_pnl_avg":null,"capital":44.65,"capital_pct":-25.6},{"name":"q_anchor_20","closed":15,"mature":false,"win":33.3,"rug":66.7,"per_trade":null,"open":0,"open_value":0,"open_pnl_avg":null,"capital":44.41,"capital_pct":-26.0},{"name":"q_quiet","closed":37,"mature":true,"win":51.4,"rug":27.0,"per_trade":-0.43,"open":0,"open_value":0,"open_pnl_avg":null,"capital":44.07,"capital_pct":-26.5},{"name":"q_edge_deep","closed":21,"mature":true,"win":52.4,"rug":47.6,"per_trade":-0.879,"open":0,"open_value":0,"open_pnl_avg":null,"capital":41.55,"capital_pct":-30.8},{"name":"q_combo","closed":140,"mature":true,"win":54.3,"rug":37.9,"per_trade":-0.135,"open":0,"open_value":0,"open_pnl_avg":null,"capital":41.03,"capital_pct":-31.6},{"name":"q_balance","closed":229,"mature":true,"win":51.1,"rug":24.5,"per_trade":-0.093,"open":0,"open_value":0,"open_pnl_avg":null,"capital":38.63,"capital_pct":-35.6},{"name":"q_02","closed":173,"mature":true,"win":52.0,"rug":43.9,"per_trade":-0.124,"open":0,"open_value":0,"open_pnl_avg":null,"capital":38.49,"capital_pct":-35.9},{"name":"q_lowrug","closed":22,"mature":true,"win":36.4,"rug":59.1,"per_trade":-0.983,"open":0,"open_value":0,"open_pnl_avg":null,"capital":38.38,"capital_pct":-36.0},{"name":"q_balance_ride","closed":33,"mature":true,"win":39.4,"rug":42.4,"per_trade":-0.87,"open":0,"open_value":0,"open_pnl_avg":null,"capital":31.28,"capital_pct":-47.9},{"name":"q_anchor_40","closed":20,"mature":true,"win":25.0,"rug":75.0,"per_trade":-1.461,"open":0,"open_value":0,"open_pnl_avg":null,"capital":30.78,"capital_pct":-48.7},{"name":"q_fable5_deep100","closed":17,"mature":false,"win":17.6,"rug":82.4,"per_trade":null,"open":0,"open_value":0,"open_pnl_avg":null,"capital":29.39,"capital_pct":-51.0},{"name":"q_balance_wide","closed":49,"mature":true,"win":40.8,"rug":38.8,"per_trade":-0.706,"open":0,"open_value":0,"open_pnl_avg":null,"capital":25.38,"capital_pct":-57.7},{"name":"q_apex_20","closed":248,"mature":true,"win":52.8,"rug":42.3,"per_trade":-0.141,"open":0,"open_value":0,"open_pnl_avg":null,"capital":25.14,"capital_pct":-58.1},{"name":"q_apex_40","closed":248,"mature":true,"win":52.8,"rug":42.3,"per_trade":-0.141,"open":0,"open_value":0,"open_pnl_avg":null,"capital":25.12,"capital_pct":-58.1},{"name":"q_nova","closed":204,"mature":true,"win":54.9,"rug":39.2,"per_trade":-0.19,"open":0,"open_value":0,"open_pnl_avg":null,"capital":21.31,"capital_pct":-64.5},{"name":"q_sweet","closed":128,"mature":true,"win":47.7,"rug":46.1,"per_trade":-0.431,"open":0,"open_value":0,"open_pnl_avg":null,"capital":4.89,"capital_pct":-91.9},{"name":"q_titan","closed":174,"mature":true,"win":48.3,"rug":47.1,"per_trade":-0.326,"open":0,"open_value":0,"open_pnl_avg":null,"capital":3.29,"capital_pct":-94.5},{"name":"q_prime_20","closed":237,"mature":true,"win":46.0,"rug":48.1,"per_trade":-0.263,"open":0,"open_value":0,"open_pnl_avg":null,"capital":-2.33,"capital_pct":-103.9},{"name":"q_prime_40","closed":237,"mature":true,"win":46.0,"rug":48.1,"per_trade":-0.263,"open":0,"open_value":0,"open_pnl_avg":null,"capital":-2.41,"capital_pct":-104.0},{"name":"q_trifecta_20","closed":264,"mature":true,"win":54.2,"rug":42.4,"per_trade":-0.238,"open":0,"open_value":0,"open_pnl_avg":null,"capital":-2.78,"capital_pct":-104.6},{"name":"q_synth_40","closed":267,"mature":true,"win":49.8,"rug":44.2,"per_trade":-0.24,"open":0,"open_value":0,"open_pnl_avg":null,"capital":-3.99,"capital_pct":-106.7},{"name":"q_trifecta_40","closed":273,"mature":true,"win":53.5,"rug":42.5,"per_trade":-0.26,"open":0,"open_value":0,"open_pnl_avg":null,"capital":-10.94,"capital_pct":-118.2},{"name":"q_midmom","closed":163,"mature":true,"win":46.0,"rug":49.7,"per_trade":-0.464,"open":0,"open_value":0,"open_pnl_avg":null,"capital":-15.65,"capital_pct":-126.1},{"name":"q_apex","closed":248,"mature":true,"win":46.4,"rug":47.2,"per_trade":-0.429,"open":0,"open_value":0,"open_pnl_avg":null,"capital":-46.5,"capital_pct":-177.5},{"name":"q_fastlock","closed":307,"mature":true,"win":63.2,"rug":31.6,"per_trade":-0.358,"open":0,"open_value":0,"open_pnl_avg":null,"capital":-49.83,"capital_pct":-183.1},{"name":"q_synth","closed":267,"mature":true,"win":46.4,"rug":47.9,"per_trade":-0.444,"open":0,"open_value":0,"open_pnl_avg":null,"capital":-58.44,"capital_pct":-197.4},{"name":"q_balanced","closed":272,"mature":true,"win":46.0,"rug":48.2,"per_trade":-0.446,"open":0,"open_value":0,"open_pnl_avg":null,"capital":-61.42,"capital_pct":-202.4},{"name":"q_trifecta","closed":273,"mature":true,"win":46.2,"rug":48.4,"per_trade":-0.47,"open":0,"open_value":0,"open_pnl_avg":null,"capital":-68.18,"capital_pct":-213.6},{"name":"q_prime","closed":234,"mature":true,"win":37.2,"rug":57.3,"per_trade":-0.736,"open":0,"open_value":0,"open_pnl_avg":null,"capital":-112.19,"capital_pct":-287.0},{"name":"q_reality_40","closed":540,"mature":true,"win":48.9,"rug":45.9,"per_trade":-0.322,"open":1,"open_value":5.38,"open_pnl_avg":115.0,"capital":-113.86,"capital_pct":-289.8},{"name":"q_reality_20","closed":540,"mature":true,"win":48.9,"rug":45.9,"per_trade":-0.322,"open":1,"open_value":5.38,"open_pnl_avg":115.0,"capital":-113.88,"capital_pct":-289.8},{"name":"q_reality","closed":540,"mature":true,"win":45.9,"rug":48.5,"per_trade":-0.479,"open":1,"open_value":5.38,"open_pnl_avg":115.0,"capital":-198.51,"capital_pct":-430.8},{"name":"q_deepbook","closed":143,"mature":true,"win":18.2,"rug":76.9,"per_trade":-1.935,"open":1,"open_value":2.98,"open_pnl_avg":19.0,"capital":-216.73,"capital_pct":-461.2},{"name":"q_strict","closed":292,"mature":true,"win":30.1,"rug":68.5,"per_trade":-1.154,"open":1,"open_value":3.29,"open_pnl_avg":32.0,"capital":-277.03,"capital_pct":-561.7},{"name":"q_peak","closed":499,"mature":true,"win":36.9,"rug":56.5,"per_trade":-0.85,"open":2,"open_value":6.91,"open_pnl_avg":38.0,"capital":-364.38,"capital_pct":-707.3},{"name":"q_twoway","closed":656,"mature":true,"win":34.6,"rug":50.0,"per_trade":-0.757,"open":2,"open_value":8.36,"open_pnl_avg":67.0,"capital":-436.63,"capital_pct":-827.7},{"name":"q_deep","closed":401,"mature":true,"win":14.2,"rug":84.0,"per_trade":-2.079,"open":3,"open_value":10.73,"open_pnl_avg":43.0,"capital":-773.72,"capital_pct":-1389.5},{"name":"q_anchor","closed":707,"mature":true,"win":29.3,"rug":68.6,"per_trade":-1.225,"open":5,"open_value":13.89,"open_pnl_avg":11.0,"capital":-806.09,"capital_pct":-1443.5},{"name":"q_anchor_run","closed":707,"mature":true,"win":28.0,"rug":69.6,"per_trade":-1.392,"open":5,"open_value":13.89,"open_pnl_avg":11.0,"capital":-924.27,"capital_pct":-1640.4},{"name":"q_tight","closed":858,"mature":true,"win":24.2,"rug":69.0,"per_trade":-1.425,"open":5,"open_value":13.89,"open_pnl_avg":11.0,"capital":-1162.26,"capital_pct":-2037.1},{"name":"q_momonly","closed":1375,"mature":true,"win":28.3,"rug":45.8,"per_trade":-1.211,"open":7,"open_value":19.88,"open_pnl_avg":14.0,"capital":-1604.85,"capital_pct":-2774.8},{"name":"q_quicklock","closed":1562,"mature":true,"win":27.8,"rug":64.3,"per_trade":-1.195,"open":7,"open_value":19.04,"open_pnl_avg":9.0,"capital":-1807.12,"capital_pct":-3111.9},{"name":"q_lockcore","closed":1618,"mature":true,"win":26.7,"rug":64.5,"per_trade":-1.173,"open":7,"open_value":19.88,"open_pnl_avg":14.0,"capital":-1837.86,"capital_pct":-3163.1},{"name":"q_volconf","closed":1336,"mature":true,"win":22.7,"rug":71.3,"per_trade":-1.577,"open":7,"open_value":19.88,"open_pnl_avg":14.0,"capital":-2046.62,"capital_pct":-3511.0},{"name":"q_earlymom","closed":1403,"mature":true,"win":25.2,"rug":69.0,"per_trade":-1.514,"open":7,"open_value":19.88,"open_pnl_avg":14.0,"capital":-2064.68,"capital_pct":-3541.1},{"name":"q_patient","closed":1561,"mature":true,"win":25.0,"rug":67.5,"per_trade":-1.437,"open":7,"open_value":19.88,"open_pnl_avg":14.0,"capital":-2182.83,"capital_pct":-3738.1},{"name":"q_runner","closed":1561,"mature":true,"win":25.0,"rug":67.5,"per_trade":-1.437,"open":7,"open_value":19.88,"open_pnl_avg":14.0,"capital":-2182.83,"capital_pct":-3738.0},{"name":"q_core","closed":1564,"mature":true,"win":24.7,"rug":67.5,"per_trade":-1.441,"open":7,"open_value":19.88,"open_pnl_avg":14.0,"capital":-2194.31,"capital_pct":-3757.2},{"name":"q_scalp","closed":1614,"mature":true,"win":24.2,"rug":67.0,"per_trade":-1.443,"open":7,"open_value":19.88,"open_pnl_avg":14.0,"capital":-2269.73,"capital_pct":-3882.9},{"name":"q_score","closed":2426,"mature":true,"win":37.5,"rug":52.0,"per_trade":-1.087,"open":7,"open_value":14.61,"open_pnl_avg":-17.0,"capital":-2576.86,"capital_pct":-4394.8},{"name":"q_liqonly","closed":1954,"mature":true,"win":28.5,"rug":63.1,"per_trade":-1.42,"open":7,"open_value":14.64,"open_pnl_avg":-16.0,"capital":-2714.29,"capital_pct":-4623.8}],"open_positions":{"q_score":[{"sym":"BULLHOUSE","age_min":0.1,"size":2.5,"liq":3,"value":0.0,"pnl":-100.0,"status":"UNSELLABLE"},{"sym":"BRSCB","age_min":3.9,"size":2.5,"liq":67064,"value":2.37,"pnl":-5.0,"status":"loss"},{"sym":"Penny","age_min":6.5,"size":2.5,"liq":23318,"value":3.29,"pnl":32.0,"status":"win"},{"sym":"ZILLA","age_min":6.6,"size":2.5,"liq":19017,"value":3.09,"pnl":23.0,"status":"win"},{"sym":"BULLHOUSE","age_min":9.9,"size":2.5,"liq":24410,"value":3.62,"pnl":45.0,"status":"win"},{"sym":"NIGGABULL","age_min":37.8,"size":2.5,"liq":94997,"value":2.24,"pnl":-11.0,"status":"loss"},{"sym":"BLACKINU","age_min":40.4,"size":2.5,"liq":3,"value":0.0,"pnl":-100.0,"status":"UNSELLABLE"}],"q_liqonly":[{"sym":"BULLHOUSE","age_min":0.1,"size":2.5,"liq":3,"value":0.0,"pnl":-100.0,"status":"UNSELLABLE"},{"sym":"BRSCB","age_min":3.9,"size":2.5,"liq":67064,"value":2.37,"pnl":-5.0,"status":"loss"},{"sym":"Penny","age_min":6.5,"size":2.5,"liq":23318,"value":3.29,"pnl":32.0,"status":"win"},{"sym":"ZILLA","age_min":6.6,"size":2.5,"liq":19017,"value":3.09,"pnl":23.0,"status":"win"},{"sym":"IMT","age_min":9.9,"size":2.5,"liq":15171,"value":2.27,"pnl":-9.0,"status":"loss"},{"sym":"BULLHOUSE","age_min":9.9,"size":2.5,"liq":24410,"value":3.62,"pnl":45.0,"status":"win"},{"sym":"BLACKINU","age_min":40.4,"size":2.5,"liq":3,"value":0.0,"pnl":-100.0,"status":"UNSELLABLE"}],"widenet":[{"sym":"Jamey","age_min":0.2,"size":2.5,"liq":0,"value":2.27,"pnl":-9.0,"status":"loss"},{"sym":"W26","age_min":0.2,"size":2.5,"liq":8,"value":2.27,"pnl":-9.0,"status":"loss"},{"sym":"BDGA","age_min":1.0,"size":2.5,"liq":132115,"value":3.0,"pnl":20.0,"status":"win"},{"sym":"9PKWkc","age_min":1.1,"size":2.5,"liq":221,"value":7.5,"pnl":200.0,"status":"win"},{"sym":"NTFS","age_min":2.4,"size":2.5,"liq":67934,"value":2.63,"pnl":5.0,"status":"win"},{"sym":"USWR","age_min":2.4,"size":2.5,"liq":107518,"value":2.53,"pnl":1.0,"status":"flat"},{"sym":"BRSCB","age_min":3.9,"size":2.5,"liq":67064,"value":2.37,"pnl":-5.0,"status":"loss"},{"sym":"RUNNER","age_min":3.9,"size":2.5,"liq":20515,"value":2.71,"pnl":8.0,"status":"win"},{"sym":"HtovSn","age_min":4.6,"size":2.5,"liq":29,"value":7.5,"pnl":200.0,"status":"win"},{"sym":"HANUMANJI","age_min":5.7,"size":2.5,"liq":null,"value":2.27,"pnl":-9.0,"status":"loss"},{"sym":"GITLAB","age_min":5.7,"size":2.5,"liq":null,"value":2.27,"pnl":-9.0,"status":"loss"},{"sym":"DlET","age_min":6.6,"size":2.5,"liq":160,"value":2.09,"pnl":-17.0,"status":"loss"},{"sym":"CASHCAT","age_min":6.6,"size":2.5,"liq":50896,"value":2.97,"pnl":19.0,"status":"win"},{"sym":"BULLHOUSE","age_min":9.9,"size":2.5,"liq":24410,"value":3.62,"pnl":45.0,"status":"win"},{"sym":"$Jamey","age_min":11.5,"size":2.5,"liq":99131,"value":2.98,"pnl":19.0,"status":"win"},{"sym":"W26","age_min":12.2,"size":2.5,"liq":210868,"value":3.97,"pnl":59.0,"status":"win"},{"sym":"rotcoin","age_min":39.6,"size":2.5,"liq":0,"value":2.27,"pnl":-9.0,"status":"loss"},{"sym":"AuYmGv","age_min":40.5,"size":2.5,"liq":5,"value":0.0,"pnl":-100.0,"status":"loss"},{"sym":"GORP","age_min":41.9,"size":2.5,"liq":123426,"value":2.21,"pnl":-12.0,"status":"loss"},{"sym":"GEV","age_min":43.3,"size":2.5,"liq":983639,"value":7.5,"pnl":200.0,"status":"win"}],"q_lockcore":[{"sym":"BRSCB","age_min":3.9,"size":2.5,"liq":67064,"value":2.37,"pnl":-5.0,"status":"loss"},{"sym":"Penny","age_min":6.5,"size":2.5,"liq":23318,"value":3.29,"pnl":32.0,"status":"win"},{"sym":"ZILLA","age_min":6.6,"size":2.5,"liq":19017,"value":3.09,"pnl":23.0,"status":"win"},{"sym":"Penny","age_min":8.3,"size":2.5,"liq":20158,"value":3.69,"pnl":47.0,"status":"win"},{"sym":"BULLHOUSE","age_min":9.9,"size":2.5,"liq":24410,"value":3.62,"pnl":45.0,"status":"win"},{"sym":"\ud83d\udca2","age_min":15.2,"size":2.5,"liq":22441,"value":3.82,"pnl":53.0,"status":"win"},{"sym":"BLACKINU","age_min":40.4,"size":2.5,"liq":3,"value":0.0,"pnl":-100.0,"status":"UNSELLABLE"}],"q_quicklock":[{"sym":"BRSCB","age_min":3.9,"size":2.5,"liq":67064,"value":2.37,"pnl":-5.0,"status":"loss"},{"sym":"Penny","age_min":6.5,"size":2.5,"liq":23318,"value":3.29,"pnl":32.0,"status":"win"},{"sym":"ZILLA","age_min":6.6,"size":2.5,"liq":19017,"value":3.09,"pnl":23.0,"status":"win"},{"sym":"Penny","age_min":8.3,"size":2.5,"liq":20158,"value":3.69,"pnl":47.0,"status":"win"},{"sym":"BULLHOUSE","age_min":9.9,"size":2.5,"liq":24410,"value":3.62,"pnl":45.0,"status":"win"},{"sym":"$Jamey","age_min":11.5,"size":2.5,"liq":99131,"value":2.98,"pnl":19.0,"status":"win"},{"sym":"BLACKINU","age_min":40.4,"size":2.5,"liq":3,"value":0.0,"pnl":-100.0,"status":"UNSELLABLE"}],"q_deep":[{"sym":"BRSCB","age_min":3.9,"size":2.5,"liq":67064,"value":2.37,"pnl":-5.0,"status":"loss"},{"sym":"$Jamey","age_min":11.5,"size":2.5,"liq":99131,"value":2.98,"pnl":19.0,"status":"win"},{"sym":"GUGA","age_min":18.1,"size":2.5,"liq":156776,"value":5.38,"pnl":115.0,"status":"win"}],"q_earlymom":[{"sym":"BRSCB","age_min":3.9,"size":2.5,"liq":67064,"value":2.37,"pnl":-5.0,"status":"loss"},{"sym":"Penny","age_min":6.5,"size":2.5,"liq":23318,"value":3.29,"pnl":32.0,"status":"win"},{"sym":"ZILLA","age_min":6.6,"size":2.5,"liq":19017,"value":3.09,"pnl":23.0,"status":"win"},{"sym":"Penny","age_min":8.3,"size":2.5,"liq":20158,"value":3.69,"pnl":47.0,"status":"win"},{"sym":"BULLHOUSE","age_min":9.9,"size":2.5,"liq":24410,"value":3.62,"pnl":45.0,"status":"win"},{"sym":"\ud83d\udca2","age_min":15.2,"size":2.5,"liq":22441,"value":3.82,"pnl":53.0,"status":"win"},{"sym":"BLACKINU","age_min":40.4,"size":2.5,"liq":3,"value":0.0,"pnl":-100.0,"status":"UNSELLABLE"}],"q_runner":[{"sym":"BRSCB","age_min":3.9,"size":2.5,"liq":67064,"value":2.37,"pnl":-5.0,"status":"loss"},{"sym":"Penny","age_min":6.5,"size":2.5,"liq":23318,"value":3.29,"pnl":32.0,"status":"win"},{"sym":"ZILLA","age_min":6.6,"size":2.5,"liq":19017,"value":3.09,"pnl":23.0,"status":"win"},{"sym":"Penny","age_min":8.3,"size":2.5,"liq":20158,"value":3.69,"pnl":47.0,"status":"win"},{"sym":"BULLHOUSE","age_min":9.9,"size":2.5,"liq":24410,"value":3.62,"pnl":45.0,"status":"win"},{"sym":"\ud83d\udca2","age_min":15.2,"size":2.5,"liq":22441,"value":3.82,"pnl":53.0,"status":"win"},{"sym":"BLACKINU","age_min":40.4,"size":2.5,"liq":3,"value":0.0,"pnl":-100.0,"status":"UNSELLABLE"}],"q_volconf":[{"sym":"BRSCB","age_min":3.9,"size":2.5,"liq":67064,"value":2.37,"pnl":-5.0,"status":"loss"},{"sym":"Penny","age_min":6.5,"size":2.5,"liq":23318,"value":3.29,"pnl":32.0,"status":"win"},{"sym":"ZILLA","age_min":6.6,"size":2.5,"liq":19017,"value":3.09,"pnl":23.0,"status":"win"},{"sym":"Penny","age_min":8.3,"size":2.5,"liq":20158,"value":3.69,"pnl":47.0,"status":"win"},{"sym":"BULLHOUSE","age_min":9.9,"size":2.5,"liq":24410,"value":3.62,"pnl":45.0,"status":"win"},{"sym":"\ud83d\udca2","age_min":15.2,"size":2.5,"liq":22441,"value":3.82,"pnl":53.0,"status":"win"},{"sym":"BLACKINU","age_min":40.4,"size":2.5,"liq":3,"value":0.0,"pnl":-100.0,"status":"UNSELLABLE"}],"q_scalp":[{"sym":"BRSCB","age_min":3.9,"size":2.5,"liq":67064,"value":2.37,"pnl":-5.0,"status":"loss"},{"sym":"Penny","age_min":6.5,"size":2.5,"liq":23318,"value":3.29,"pnl":32.0,"status":"win"},{"sym":"ZILLA","age_min":6.6,"size":2.5,"liq":19017,"value":3.09,"pnl":23.0,"status":"win"},{"sym":"Penny","age_min":8.3,"size":2.5,"liq":20158,"value":3.69,"pnl":47.0,"status":"win"},{"sym":"BULLHOUSE","age_min":9.9,"size":2.5,"liq":24410,"value":3.62,"pnl":45.0,"status":"win"},{"sym":"\ud83d\udca2","age_min":15.2,"size":2.5,"liq":22441,"value":3.82,"pnl":53.0,"status":"win"},{"sym":"BLACKINU","age_min":40.4,"size":2.5,"liq":3,"value":0.0,"pnl":-100.0,"status":"UNSELLABLE"}],"q_patient":[{"sym":"BRSCB","age_min":3.9,"size":2.5,"liq":67064,"value":2.37,"pnl":-5.0,"status":"loss"},{"sym":"Penny","age_min":6.5,"size":2.5,"liq":23318,"value":3.29,"pnl":32.0,"status":"win"},{"sym":"ZILLA","age_min":6.6,"size":2.5,"liq":19017,"value":3.09,"pnl":23.0,"status":"win"},{"sym":"Penny","age_min":8.3,"size":2.5,"liq":20158,"value":3.69,"pnl":47.0,"status":"win"},{"sym":"BULLHOUSE","age_min":9.9,"size":2.5,"liq":24410,"value":3.62,"pnl":45.0,"status":"win"},{"sym":"\ud83d\udca2","age_min":15.2,"size":2.5,"liq":22441,"value":3.82,"pnl":53.0,"status":"win"},{"sym":"BLACKINU","age_min":40.4,"size":2.5,"liq":3,"value":0.0,"pnl":-100.0,"status":"UNSELLABLE"}],"q_momonly":[{"sym":"BRSCB","age_min":3.9,"size":2.5,"liq":67064,"value":2.37,"pnl":-5.0,"status":"loss"},{"sym":"Penny","age_min":6.5,"size":2.5,"liq":23318,"value":3.29,"pnl":32.0,"status":"win"},{"sym":"ZILLA","age_min":6.6,"size":2.5,"liq":19017,"value":3.09,"pnl":23.0,"status":"win"},{"sym":"Penny","age_min":8.3,"size":2.5,"liq":20158,"value":3.69,"pnl":47.0,"status":"win"},{"sym":"BULLHOUSE","age_min":9.9,"size":2.5,"liq":24410,"value":3.62,"pnl":45.0,"status":"win"},{"sym":"\ud83d\udca2","age_min":15.2,"size":2.5,"liq":22441,"value":3.82,"pnl":53.0,"status":"win"},{"sym":"BLACKINU","age_min":40.4,"size":2.5,"liq":3,"value":0.0,"pnl":-100.0,"status":"UNSELLABLE"}],"q_core":[{"sym":"BRSCB","age_min":3.9,"size":2.5,"liq":67064,"value":2.37,"pnl":-5.0,"status":"loss"},{"sym":"Penny","age_min":6.5,"size":2.5,"liq":23318,"value":3.29,"pnl":32.0,"status":"win"},{"sym":"ZILLA","age_min":6.6,"size":2.5,"liq":19017,"value":3.09,"pnl":23.0,"status":"win"},{"sym":"Penny","age_min":8.3,"size":2.5,"liq":20158,"value":3.69,"pnl":47.0,"status":"win"},{"sym":"BULLHOUSE","age_min":9.9,"size":2.5,"liq":24410,"value":3.62,"pnl":45.0,"status":"win"},{"sym":"\ud83d\udca2","age_min":15.2,"size":2.5,"liq":22441,"value":3.82,"pnl":53.0,"status":"win"},{"sym":"BLACKINU","age_min":40.4,"size":2.5,"liq":3,"value":0.0,"pnl":-100.0,"status":"UNSELLABLE"}],"q_anchor_run":[{"sym":"Penny","age_min":6.5,"size":2.5,"liq":23318,"value":3.29,"pnl":32.0,"status":"win"},{"sym":"ZILLA","age_min":6.6,"size":2.5,"liq":19017,"value":3.09,"pnl":23.0,"status":"win"},{"sym":"Penny","age_min":8.3,"size":2.5,"liq":20158,"value":3.69,"pnl":47.0,"status":"win"},{"sym":"\ud83d\udca2","age_min":15.2,"size":2.5,"liq":22441,"value":3.82,"pnl":53.0,"status":"win"},{"sym":"BLACKINU","age_min":40.4,"size":2.5,"liq":3,"value":0.0,"pnl":-100.0,"status":"UNSELLABLE"}],"q_anchor":[{"sym":"Penny","age_min":6.5,"size":2.5,"liq":23318,"value":3.29,"pnl":32.0,"status":"win"},{"sym":"ZILLA","age_min":6.6,"size":2.5,"liq":19017,"value":3.09,"pnl":23.0,"status":"win"},{"sym":"Penny","age_min":8.3,"size":2.5,"liq":20158,"value":3.69,"pnl":47.0,"status":"win"},{"sym":"\ud83d\udca2","age_min":15.2,"size":2.5,"liq":22441,"value":3.82,"pnl":53.0,"status":"win"},{"sym":"BLACKINU","age_min":40.4,"size":2.5,"liq":3,"value":0.0,"pnl":-100.0,"status":"UNSELLABLE"}],"q_peak":[{"sym":"Penny","age_min":6.5,"size":2.5,"liq":23318,"value":3.29,"pnl":32.0,"status":"win"},{"sym":"BULLHOUSE","age_min":9.9,"size":2.5,"liq":24410,"value":3.62,"pnl":45.0,"status":"win"}],"q_strict":[{"sym":"Penny","age_min":6.5,"size":2.5,"liq":23318,"value":3.29,"pnl":32.0,"status":"win"}],"q_tight":[{"sym":"Penny","age_min":6.5,"size":2.5,"liq":23318,"value":3.29,"pnl":32.0,"status":"win"},{"sym":"ZILLA","age_min":6.6,"size":2.5,"liq":19017,"value":3.09,"pnl":23.0,"status":"win"},{"sym":"Penny","age_min":8.3,"size":2.5,"liq":20158,"value":3.69,"pnl":47.0,"status":"win"},{"sym":"\ud83d\udca2","age_min":15.2,"size":2.5,"liq":22441,"value":3.82,"pnl":53.0,"status":"win"},{"sym":"BLACKINU","age_min":40.4,"size":2.5,"liq":3,"value":0.0,"pnl":-100.0,"status":"UNSELLABLE"}],"q_deepbook":[{"sym":"$Jamey","age_min":11.5,"size":2.5,"liq":99131,"value":2.98,"pnl":19.0,"status":"win"}],"q_twoway":[{"sym":"$Jamey","age_min":11.5,"size":2.5,"liq":99131,"value":2.98,"pnl":19.0,"status":"win"},{"sym":"GUGA","age_min":18.1,"size":2.5,"liq":156776,"value":5.38,"pnl":115.0,"status":"win"}],"q_reality_40":[{"sym":"GUGA","age_min":18.1,"size":2.5,"liq":156776,"value":5.38,"pnl":115.0,"status":"win"}],"q_reality_20":[{"sym":"GUGA","age_min":18.1,"size":2.5,"liq":156776,"value":5.38,"pnl":115.0,"status":"win"}],"q_reality":[{"sym":"GUGA","age_min":18.1,"size":2.5,"liq":156776,"value":5.38,"pnl":115.0,"status":"win"}]},"feed":[{"strat":"q_liqonly","sym":"Penny","ago_min":0.1,"reason":"reality_rotate_lock","pnl":42.0},{"strat":"q_score","sym":"Penny","ago_min":0.1,"reason":"reality_rotate_lock","pnl":42.0},{"strat":"widenet","sym":"FtxMtQ","ago_min":0.3,"reason":"max_age_widenet","pnl":-21.0},{"strat":"widenet","sym":"W26","ago_min":0.3,"reason":"stop_loss","pnl":-100.0},{"strat":"q_tight","sym":"Jamey","ago_min":1.8,"reason":"paper_rug","pnl":-98.0},{"strat":"q_anchor","sym":"Jamey","ago_min":1.8,"reason":"paper_rug","pnl":-98.0},{"strat":"q_anchor_run","sym":"Jamey","ago_min":1.8,"reason":"paper_rug","pnl":-98.0},{"strat":"widenet","sym":"Jamey","ago_min":1.8,"reason":"stop_loss","pnl":-54.0},{"strat":"widenet","sym":"GPS","ago_min":1.9,"reason":"max_age_widenet","pnl":-1.0},{"strat":"widenet","sym":"USD1","ago_min":1.9,"reason":"max_age_widenet","pnl":-1.0},{"strat":"widenet","sym":"GEV","ago_min":2.6,"reason":"max_age_widenet","pnl":-2.0},{"strat":"widenet","sym":"ROBINDROP","ago_min":3.4,"reason":"max_age_widenet","pnl":-1.0},{"strat":"q_core","sym":"GUGA","ago_min":3.9,"reason":"reality_rotate_lock","pnl":44.0},{"strat":"q_momonly","sym":"GUGA","ago_min":3.9,"reason":"reality_rotate_lock","pnl":44.0},{"strat":"q_patient","sym":"GUGA","ago_min":3.9,"reason":"reality_rotate_lock","pnl":44.0},{"strat":"q_scalp","sym":"GUGA","ago_min":3.9,"reason":"reality_rotate_lock","pnl":44.0},{"strat":"q_volconf","sym":"GUGA","ago_min":3.9,"reason":"reality_rotate_lock","pnl":44.0},{"strat":"q_runner","sym":"GUGA","ago_min":3.9,"reason":"reality_rotate_lock","pnl":44.0},{"strat":"q_earlymom","sym":"GUGA","ago_min":3.9,"reason":"reality_rotate_lock","pnl":44.0},{"strat":"q_lockcore","sym":"GUGA","ago_min":3.9,"reason":"reality_rotate_lock","pnl":44.0},{"strat":"q_quicklock","sym":"\ud83d\udca2","ago_min":3.9,"reason":"reality_rotate_lock","pnl":27.0},{"strat":"q_liqonly","sym":"BULLHOUSE","ago_min":3.9,"reason":"reality_rotate_lock","pnl":26.0},{"strat":"q_score","sym":"BULLHOUSE","ago_min":3.9,"reason":"reality_rotate_lock","pnl":26.0},{"strat":"widenet","sym":"ANSEM","ago_min":4.1,"reason":"paper_rug","pnl":-100.0},{"strat":"widenet","sym":"XLM","ago_min":4.1,"reason":"stop_loss","pnl":-42.0},{"strat":"widenet","sym":"ANSEM","ago_min":4.9,"reason":"max_age_widenet","pnl":-1.0},{"strat":"widenet","sym":"Summer","ago_min":6.4,"reason":"max_age_widenet","pnl":-21.0},{"strat":"widenet","sym":"\u590f\u5929","ago_min":6.4,"reason":"max_age_widenet","pnl":-21.0},{"strat":"q_core","sym":"Jamey","ago_min":6.6,"reason":"reality_rotate_lock","pnl":49.0},{"strat":"q_momonly","sym":"Jamey","ago_min":6.6,"reason":"reality_rotate_lock","pnl":49.0},{"strat":"q_patient","sym":"Jamey","ago_min":6.6,"reason":"reality_rotate_lock","pnl":49.0},{"strat":"q_scalp","sym":"Jamey","ago_min":6.6,"reason":"reality_rotate_lock","pnl":49.0},{"strat":"q_volconf","sym":"Jamey","ago_min":6.6,"reason":"reality_rotate_lock","pnl":49.0},{"strat":"q_runner","sym":"Jamey","ago_min":6.6,"reason":"reality_rotate_lock","pnl":49.0},{"strat":"q_earlymom","sym":"Jamey","ago_min":6.6,"reason":"reality_rotate_lock","pnl":49.0},{"strat":"q_lockcore","sym":"Jamey","ago_min":6.6,"reason":"reality_rotate_lock","pnl":49.0},{"strat":"q_quicklock","sym":"GUGA","ago_min":6.6,"reason":"reality_rotate_lock","pnl":28.0},{"strat":"q_liqonly","sym":"$Jamey","ago_min":6.6,"reason":"reality_rotate_lock","pnl":22.0},{"strat":"q_score","sym":"$Jamey","ago_min":6.6,"reason":"reality_rotate_lock","pnl":22.0},{"strat":"q_quicklock","sym":"Jamey","ago_min":6.6,"reason":"reality_rotate_lock","pnl":49.0},{"strat":"q_liqonly","sym":"GUGA","ago_min":6.6,"reason":"reality_rotate_lock","pnl":28.0},{"strat":"q_score","sym":"GUGA","ago_min":6.6,"reason":"reality_rotate_lock","pnl":28.0},{"strat":"widenet","sym":"ZILLA","ago_min":7.1,"reason":"max_age_widenet","pnl":-21.0},{"strat":"widenet","sym":"GROK","ago_min":7.1,"reason":"max_age_widenet","pnl":-100.0},{"strat":"widenet","sym":"USA250","ago_min":7.1,"reason":"max_age_widenet","pnl":-2.0},{"strat":"widenet","sym":"ANSEM","ago_min":7.9,"reason":"paper_rug","pnl":-100.0},{"strat":"q_liqonly","sym":"\ud83d\udca2","ago_min":8.4,"reason":"reality_rotate_lock","pnl":19.0},{"strat":"q_score","sym":"\ud83d\udca2","ago_min":8.4,"reason":"reality_rotate_lock","pnl":19.0},{"strat":"q_core","sym":"OARPOL","ago_min":9.5,"reason":"paper_rug","pnl":-98.0},{"strat":"q_momonly","sym":"OARPOL","ago_min":9.5,"reason":"paper_rug","pnl":-98.0}],"note":"FRESH START (reset 2026-07-04 01:29 UTC): $60 bankroll, $2.5/trade LIVE reality. Rug/honeypot/noprice=-100%, moon +200% cap, real fees+slippage+$0.12 gas. Prior history archived."}